calendar_app/__init__.py
calendar_app/cli.py
calendar_app/models/__init__.py
calendar_app/models/event_store.py
calendar_app/models/formatters.py
calendar_app/renderers/__init__.py
calendar_app/renderers/calendar_list.py
calendar_app/renderers/markdown.py
calendar_app/tools/__init__.py
calendar_app/tools/mcp_server.py
calendar_app/utils/__init__.py
calendar_app/utils/date_utils.py
calendar_app_mcp-0.2.2.dist-info/METADATA
calendar_app_mcp-0.2.2.dist-info/WHEEL
calendar_app_mcp-0.2.2.dist-info/entry_points.txt
calendar_app_mcp-0.2.2.dist-info/licenses/LICENSE
calendar_app_mcp-0.2.2.dist-info/RECORD
