Metadata-Version: 2.4
Name: calendar-app-mcp
Version: 0.2.2
Summary: Calendar app MCP for accessing macOS Calendar events and reminders
Project-URL: Homepage, https://github.com/rygwdn/calendar-app-mcp
Project-URL: Bug Tracker, https://github.com/rygwdn/calendar-app-mcp/issues
Project-URL: Source Code, https://github.com/rygwdn/calendar-app-mcp
Author-email: Ryan Wooden <rygwdn@gmail.com>
License: MIT
License-File: LICENSE
Keywords: ai,assistant,calendar,claude,macos,mcp
Classifier: Development Status :: 4 - Beta
Classifier: Intended Audience :: Developers
Classifier: License :: OSI Approved :: MIT License
Classifier: Operating System :: MacOS :: MacOS X
Classifier: Programming Language :: Python :: 3
Classifier: Programming Language :: Python :: 3.12
Classifier: Topic :: Office/Business :: Scheduling
Classifier: Topic :: Software Development :: Libraries :: Python Modules
Classifier: Topic :: Utilities
Requires-Python: >=3.12
Requires-Dist: fastmcp>=2.2.0
Requires-Dist: jinja2>=3.1.6
Requires-Dist: pyobjc-framework-eventkit>=11.0
Requires-Dist: pytz>=2024.1
Provides-Extra: dev
Requires-Dist: black>=25.1.0; extra == 'dev'
Requires-Dist: build>=1.2.2; extra == 'dev'
Requires-Dist: pytest-black>=0.6.0; extra == 'dev'
Requires-Dist: pytest-cov>=6.1.1; extra == 'dev'
Requires-Dist: pytest-mock>=3.14.0; extra == 'dev'
Requires-Dist: pytest-ruff>=0.4.1; extra == 'dev'
Requires-Dist: pytest>=8.3.5; extra == 'dev'
Requires-Dist: ruff>=0.11.6; extra == 'dev'
Requires-Dist: twine>=6.1.0; extra == 'dev'
